[
  {
    "turma": "23A",
    "n_matricula": "1",
    "nome": "João",
    "disciplina": "Matemática",
    "atividade_extra":"algebra_1",
    "docente": "Prof. Marcos",
    "status": "Aprovado"
  },
  {
    "turma": "23A",
    "n_matricula": "2",
    "nome": "Maria",
    "disciplina": "Português",
    "atividade_extra":"algebra_2",
    "docente": "Prof. Marcos",
    "status": "Reprovado"
  },
  {
    "turma": "23A",
    "n_matricula": "3",
    "nome": "Pedro",
    "disciplina": "Física",
    "atividade_extra":"algebra_3",
    "docente": "Prof. Marcos",
    "status": "Aprovado"
  }
]